Metadata-Version: 1.1
Name: tawdry
Version: 0.0.2
Summary: Type Annotated Web framework emphasizing Dont Repeat Yourself
Home-page: https://github.com/dancardin/tawdry
Author: Dan Cardin
Author-email: ddcardin@gmail.com
License: Apache2
Platform: UNKNOWN
Classifier: Development Status :: 3 - Alpha
Classifier: Environment :: Console
Classifier: Intended Audience :: Developers
Classifier: License :: OSI Approved :: Apache Software License
Classifier: Operating System :: Unix
Classifier: Programming Language :: Python :: 3.5
Classifier: Topic :: Internet :: WWW/HTTP :: WSGI
